edc_qol/.DS_Store
edc_qol/__init__.py
edc_qol/admin/__init__.py
edc_qol/admin/eq5d3l_admin.py
edc_qol/admin/icecapa_admin.py
edc_qol/admin/sf12_admin.py
edc_qol/admin_site.py
edc_qol/apps.py
edc_qol/auth_objects.py
edc_qol/auths.py
edc_qol/choices.py
edc_qol/constants.py
edc_qol/forms/__init__.py
edc_qol/forms/eq5d3l_form.py
edc_qol/forms/icecapa_form.py
edc_qol/forms/sf12_form.py
edc_qol/locale/.DS_Store
edc_qol/locale/lg/.DS_Store
edc_qol/locale/lg/LC_MESSAGES/.DS_Store
edc_qol/locale/lg/LC_MESSAGES/django.mo
edc_qol/locale/lg/LC_MESSAGES/django.po
edc_qol/locale/sw/LC_MESSAGES/django.mo
edc_qol/locale/sw/LC_MESSAGES/django.po
edc_qol/migrations/0001_initial.py
edc_qol/migrations/0002_historicalsf12_sf12.py
edc_qol/migrations/0003_auto_20220704_1841.py
edc_qol/migrations/0004_icecapa_historicalicecapa.py
edc_qol/migrations/0005_alter_historicalicecapa_enjoyment_and_more.py
edc_qol/migrations/0006_alter_eq5d3l_options_alter_icecapa_options_and_more.py
edc_qol/migrations/0007_alter_eq5d3l_managers_alter_icecapa_managers_and_more.py
edc_qol/migrations/0008_alter_eq5d3l_device_created_and_more.py
edc_qol/migrations/0009_alter_historicalsf12_felt_calm_peaceful_and_more.py
edc_qol/migrations/0010_alter_eq5d3l_options_alter_icecapa_options_and_more.py
edc_qol/migrations/0011_alter_eq5d3l_site_alter_historicaleq5d3l_site_and_more.py
edc_qol/migrations/0012_alter_eq5d3l_device_created_and_more.py
edc_qol/migrations/__init__.py
edc_qol/model_mixins/__init__.py
edc_qol/model_mixins/eq5d3l_model_mixin.py
edc_qol/model_mixins/icecapa_model_mixin.py
edc_qol/model_mixins/sf12_model_mixin.py
edc_qol/modeladmin_mixins/__init__.py
edc_qol/modeladmin_mixins/eq5d3l_model_admin_mixin.py
edc_qol/modeladmin_mixins/icecapa_model_admin_mixin.py
edc_qol/models/__init__.py
edc_qol/models/eq5d3l.py
edc_qol/models/icecapa.py
edc_qol/models/sf12.py
edc_qol/urls.py
edc_qol/utils.py
edc_qol-1.4.0.dist-info/licenses/LICENSE
edc_qol-1.4.0.dist-info/WHEEL
edc_qol-1.4.0.dist-info/METADATA
edc_qol-1.4.0.dist-info/RECORD
